fastapistats/__init__.py
fastapistats/stats.py
fast_api_stats-0.0.4.dist-info/METADATA
fast_api_stats-0.0.4.dist-info/WHEEL
fast_api_stats-0.0.4.dist-info/top_level.txt
fast_api_stats-0.0.4.dist-info/RECORD
