Metadata-Version: 2.1
Name: fast-api-stats
Version: 0.0.4
Summary: Simple stats for fastapi api
Home-page: https://github.com/FusionSid/API-Stats
Author: Siddhesh Zantye
Author-email: siddheshadsv@icloud.com
License: UNKNOWN
Platform: UNKNOWN
